exporter/__init__.py
exporter/__main__.py
exporter/cli.py
exporter/config.py
exporter/exeptions.py
exporter/helpers.py
exporter/logger.py
exporter/logic.py
fit_ctu_gitlab_exporter-1.0.0.dist-info/LICENSE
fit_ctu_gitlab_exporter-1.0.0.dist-info/METADATA
fit_ctu_gitlab_exporter-1.0.0.dist-info/WHEEL
fit_ctu_gitlab_exporter-1.0.0.dist-info/entry_points.txt
fit_ctu_gitlab_exporter-1.0.0.dist-info/top_level.txt
fit_ctu_gitlab_exporter-1.0.0.dist-info/RECORD
